pelican/__init__.py
pelican/layers.py
pelican/nets.py
pelican/primitives.py
pelican/utils.py
pelican_lite-1.1.4.dist-info/licenses/LICENSE
pelican_lite-1.1.4.dist-info/METADATA
pelican_lite-1.1.4.dist-info/WHEEL
pelican_lite-1.1.4.dist-info/top_level.txt
pelican_lite-1.1.4.dist-info/RECORD
