Metadata-Version: 2.4
Name: pelican-lite
Version: 1.1.4
Summary: Efficient reimplementation of PELICAN (Permutation-Equivariant and Lorentz-Invariant or Covariant Aggregator Network for Particle Physics)
Author-email: Jonas Spinner <j.spinner@thphys.uni-heidelberg.de>
Project-URL: homepage, https://heidelberg-hepml.github.io/pelican-lite
Project-URL: repository, https://github.com/heidelberg-hepml/pelican-lite
Requires-Python: >=3.10
License-File: LICENSE
Requires-Dist: torch>=2.0
Provides-Extra: dev
Requires-Dist: pytest; extra == "dev"
Requires-Dist: pytest-cov; extra == "dev"
Requires-Dist: sphinx<9.0; extra == "dev"
Requires-Dist: sphinx-autodoc-typehints; extra == "dev"
Requires-Dist: sphinx-rtd-theme; extra == "dev"
Dynamic: license-file
